text_scrambler/__init__.py
text_scrambler/__main__.py
text_scrambler/dictionaries.py
text_scrambler/text_scrambler.py
text_scrambler/txt_files/confusablesSummary.txt
text_scrambler-0.1.5.dist-info/AUTHORS.rst
text_scrambler-0.1.5.dist-info/LICENSE.txt
text_scrambler-0.1.5.dist-info/METADATA
text_scrambler-0.1.5.dist-info/WHEEL
text_scrambler-0.1.5.dist-info/top_level.txt
text_scrambler-0.1.5.dist-info/RECORD
