Metadata-Version: 2.1
Name: text-scrambler
Version: 0.1.5
Summary: text_scrambler, a tool to scramble texts
Home-page: https://text-scrambler.readthedocs.io
Author: GLNB
Author-email: glnb.dev@gmail.com
License: MIT
Project-URL: Documentation, https://text-scrambler.readthedocs.io
Project-URL: Source, https://github.com/GuillaumeLNB/text-scrambler
Platform: UNKNOWN
